ig_trading_lib/__init__.py
ig_trading_lib/account/__init__.py
ig_trading_lib/authentication/__init__.py
ig_trading_lib/authentication/cache.py
ig_trading_lib/authentication/models.py
ig_trading_lib/authentication/service.py
ig_trading_lib/markets/__init__.py
ig_trading_lib/trading/__init__.py
ig_trading_lib/trading/client.py
ig_trading_lib/trading/confirms.py
ig_trading_lib/trading/models.py
ig_trading_lib/trading/orders_models.py
ig_trading_lib/trading/orders_service.py
ig_trading_lib/trading/positions_models.py
ig_trading_lib/trading/positions_service.py
ig_trading_lib-2.1.0.dist-info/METADATA
ig_trading_lib-2.1.0.dist-info/WHEEL
ig_trading_lib-2.1.0.dist-info/licenses/LICENSE
ig_trading_lib-2.1.0.dist-info/RECORD
