Metadata-Version: 2.4
Name: ig-trading-lib
Version: 2.1.0
Summary: 
License: MIT
License-File: LICENSE
Author: Evgeny Aleshin
Requires-Python: >=3.13
Classifier: License :: OSI Approved :: MIT License
Classifier: Programming Language :: Python :: 3
Classifier: Programming Language :: Python :: 3.13
Classifier: Programming Language :: Python :: 3.14
Requires-Dist: cryptography (>=46.0.1,<47.0.0)
Requires-Dist: pydantic (>=2.11.9,<3.0.0)
Requires-Dist: python-dotenv (>=1.1.1,<2.0.0)
Requires-Dist: requests (>=2.32.5,<3.0.0)
